Metadata-Version: 2.4
Name: dev-anket-bharat-laiser
Version: 1.0.0
Summary: Leveraging Artificial Intelligence for Skills Extraction and Research
Author-email: LAiSER Team <PSCWP@gwu.edu>
License-Expression: BSD-3-Clause
Project-URL: Homepage, https://github.com/LAiSER-Software/extract-module
Project-URL: Repository, https://github.com/LAiSER-Software/extract-module
Project-URL: Documentation, https://github.com/LAiSER-Software/extract-module/blob/main/README.md
Project-URL: Bug Reports, https://github.com/LAiSER-Software/extract-module/issues
Classifier: Development Status :: 4 - Beta
Classifier: Intended Audience :: Developers
Classifier: Intended Audience :: Science/Research
Classifier: Operating System :: OS Independent
Classifier: Programming Language :: Python :: 3
Classifier: Programming Language :: Python :: 3.8
Classifier: Programming Language :: Python :: 3.9
Classifier: Programming Language :: Python :: 3.10
Classifier: Programming Language :: Python :: 3.11
Classifier: Programming Language :: Python :: 3.12
Classifier: Topic :: Scientific/Engineering :: Artificial Intelligence
Classifier: Topic :: Text Processing :: Linguistic
Requires-Python: >=3.8
License-File: LICENSE
Requires-Dist: torch>=1.9.0
Requires-Dist: transformers>=4.20.0
Requires-Dist: pandas>=1.3.0
Requires-Dist: numpy>=1.21.0
Requires-Dist: sentence-transformers>=2.2.0
Requires-Dist: faiss-cpu>=1.7.0
Requires-Dist: spacy>=3.4.0
Requires-Dist: requests>=2.25.0
Requires-Dist: tqdm>=4.62.0
Requires-Dist: skillNer==1.0.3
Requires-Dist: ipython
Requires-Dist: psutil
Requires-Dist: google-generativeai==0.8.5
Provides-Extra: gpu
Requires-Dist: vllm>=0.2.0; extra == "gpu"
Provides-Extra: dev
Requires-Dist: pytest>=6.0; extra == "dev"
Requires-Dist: pytest-cov>=2.0; extra == "dev"
Requires-Dist: black>=22.0; extra == "dev"
Requires-Dist: flake8>=4.0; extra == "dev"
Requires-Dist: build>=0.8.0; extra == "dev"
Requires-Dist: twine>=4.0.0; extra == "dev"
Dynamic: license-file
